{
    "body": "<p>A halberd is similar to a 5-foot-long spear, but it also has a small, axe-like head mounted near the tip.</p>", 
    "name": "Halberd", 
    "weight": "12 lbs.", 
    "url": "pfsrd://Core Rulebook/Rules/Equipment/Weapons/Weapon Descriptions/Halberd", 
    "price": "10 gp", 
    "misc": {
        "Weapon": {
            "Weapon Class": "Two-Handed Melee Weapons", 
            "Special": "brace, trip", 
            "Dmg (S)": "1d8", 
            "Proficiency": "Martial Weapons", 
            "Critical": "&times;3", 
            "Dmg (M)": "1d10", 
            "Dmg (L)": "2d8", 
            "Type": "P or S", 
            "Dmg (T)": "1d6"
        }
    }, 
    "source": "Core Rulebook", 
    "type": "item"
}