{
    "name": "6th-Level Druid Spells", 
    "level": 6, 
    "source": "Ultimate Combat", 
    "type": "spell_list", 
    "class": "Druid", 
    "spells": [
        {
            "name": "Dust Form", 
            "description": "You become an incorporeal creature of dust for a short period of time."
        }, 
        {
            "material": [
                "<", 
                "b", 
                ">", 
                "M", 
                "<", 
                "/", 
                "b", 
                ">"
            ], 
            "name": "Stoneskin, Communal", 
            "description": "As stoneskin, but you may divide the duration among creatures touched."
        }, 
        {
            "name": "Tar Pool", 
            "description": "Converts the top layer of the ground into hot tar."
        }
    ]
}