{
    "body": "<p>A fence specializes in buying and selling hard-to-find items, magical trinkets, and stolen or illegal black-market goods (such as drugs, poisons, and other types of contraband). Though fences often keep a low profile, many folks find their services useful enough that incidental contact with a local fence won't totally besmirch one's character.</p>", 
    "name": "Fence", 
    "url": "pfsrd://Ultimate Campaign/Rules/Campaign Systems/Contacts/Types of Contacts/Fence", 
    "source": "Ultimate Campaign", 
    "abbrev": "MR 2", 
    "type": "section"
}