{
    "body": "<p class=\"stat-block\">Board games have innumerable types and variations. Siege, a strategy game where players try to surround the other's pieces, is popular with older adults, while more chaotic games like Wyvern's Race and Doppel are tavern favorites.</p>", 
    "name": "Board Game", 
    "weight": "2 lbs.", 
    "url": "pfsrd://Ultimate Equipment/Rules/Gear/Entertainment and Trade Goods/Entertainment/Board Game", 
    "price": "1 sp-10 gp", 
    "misc": {
        "null": {
            "Gear Type": "Item", 
            "Price": "1 sp&ndash;10 gp"
        }
    }, 
    "source": "Ultimate Equipment", 
    "type": "item"
}