{
    "body": "<p class=\"stat-block\">A <i>planar </i>weapon is effective against all types of extradimensional beings, able to pierce their resistance to physical harm. When used to attack outsiders, a <i>planar </i>weapon ignores 5 points of their damage reduction.</p>", 
    "name": "Planar", 
    "weight": "&mdash", 
    "cl": "9th", 
    "url": "pfsrd://Ultimate Equipment/Rules/Magic Arms and Armor/Weapon Special Abilities/Magic Weapon Special Ability Descriptions/Planar", 
    "price": "+1 bonus", 
    "misc": {
        "Construction Requirements": {
            "Cost": "+1 bonus"
        }
    }, 
    "source": "Ultimate Equipment", 
    "aura": "moderate conjuration", 
    "type": "item"
}