{
    "school": "transmutation", 
    "saving_throw": "none", 
    "name": "Heart Of The Metal", 
    "descriptor": [
        "earth"
    ], 
    "text": "<p>You lend the nature of adamantine, cold iron, or silver to the targeted weapons, with the following effects:</p><ul><li><i>Adamantine</i>The weapons overcome DR/adamantine and ignore hardness less than 20.</li>\n<li><i>Cold Iron</i>: The weapons overcome DR/cold iron.</li>\n<li><i>Silver</i>: The weapons overcome DR/silver.</li></ul><p>No other advantages or disadvantages of these metal types apply. For example, a weapon given the nature of adamantine is not automatically masterwork.</p><p>This is able to affect nonmetal weapons. If you grant the target weapons the property of cold iron, the spell lasts half as long as normal.</p>", 
    "spell_resistance": "no", 
    "level": [
        {
            "class": "Magus", 
            "level": 3
        }, 
        {
            "class": "Sorcerer", 
            "level": 3
        }, 
        {
            "class": "Wizard", 
            "level": 3
        }, 
        {
            "class": "Witch", 
            "level": 3
        }
    ], 
    "casting_time": "1 standard action", 
    "source": "Advanced Class Guide", 
    "range": "close (25 ft. + 5 ft./2 levels)", 
    "component_text": "V, S, M (a chunk of adamantine worth 100 gp, or a chunk of cold iron or silver worth 20 gp)", 
    "descriptor_text": "earth", 
    "effects": [
        {
            "text": "one weapon per level", 
            "name": "Targets"
        }
    ], 
    "components": [
        {
            "type": "V"
        }, 
        {
            "type": "S"
        }, 
        {
            "text": "a chunk of adamantine worth 100 gp, or a chunk of cold iron or silver worth 20 gp", 
            "type": "M"
        }
    ], 
    "duration": "1 minute/level (see text)", 
    "type": "spell"
}