{
    "body": "<p id=\"ready-pike\">At 5th level, a phalanx soldier can, once per day, ready a weapon with the brace property as an immediate action, gaining a +1 bonus on attack and damage rolls. For every four levels beyond 5th, this bonus increases by +1, and he can use the ability one additional time per day. He cannot use this ability when flat-footed. This ability replaces weapon training 1.</p>", 
    "name": "Ready Pike", 
    "url": "pfsrd://Advanced Players Guide/Rules/Core Classes/Fighter/Fighter Archetypes/Phalanx Soldier/Ready Pike", 
    "ability_types": {
        "ability_type": "Extraordinary"
    }, 
    "source": "Advanced Player's Guide", 
    "type": "ability"
}