{
    "name": "Oblivion Inquisition", 
    "source": "Ultimate Magic", 
    "url": "pfsrd://Ultimate Magic/Rules/Spellcasting Class Options/Inquisitor/Inquisitions/Oblivion Inquisition", 
    "type": "section", 
    "subtype": "inquisitor_inquisition", 
    "sections": [
        {
            "body": "<p>Some inquisitors believe that without faith there is only oblivion. But there are some divine servants who know enough about the darkness that lies beyond faith to use it as a tool\u2026 and a weapon.</p>", 
            "type": "section", 
            "sections": [
                {
                    "body": "<p id=\"life\">You gain a 10-foot-radius aura that helps dying creatures cling to life. Within this aura, a dying creature (including yourself) adds your Wisdom bonus to it stabilization checks (in addition to any other modifiers to stabilization checks).</p>", 
                    "name": "Life Anchor", 
                    "url": "pfsrd://Ultimate Magic/Rules/Spellcasting Class Options/Inquisitor/Inquisitions/Oblivion Inquisition/Granted Powers/Life Anchor", 
                    "ability_types": {
                        "ability_type": "Supernatural"
                    }, 
                    "source": "Ultimate Magic", 
                    "type": "ability"
                }, 
                {
                    "body": "<p id=\"stare-of-oblivion\">At 8th level, you can use <i>feeblemind</i> as a gaze attack against one creature (Will negates). This effect lasts 1d4 rounds. You can use this ability once per day at 8th level, and one additional time per day for every four levels beyond 8th.</p>", 
                    "name": "Stare of Oblivion", 
                    "url": "pfsrd://Ultimate Magic/Rules/Spellcasting Class Options/Inquisitor/Inquisitions/Oblivion Inquisition/Granted Powers/Stare of Oblivion", 
                    "ability_types": {
                        "ability_type": "Spell-Like"
                    }, 
                    "source": "Ultimate Magic", 
                    "type": "ability"
                }
            ], 
            "name": "Granted Powers", 
            "source": "Ultimate Magic"
        }
    ]
}