{
    "body": "<p id=\"waraxe,-dwarven-double\">This hefty waraxe is similar to the common dwarven waraxe, but its recurved blade spans forward and back from its head like a deadly butterfly. A dwarven double waraxe grants a +1 bonus on all attack rolls after the first when using Cleave or Great Cleave.</p>", 
    "name": "Waraxe, Dwarven Double", 
    "weight": "12 lbs.", 
    "url": "pfsrd://Advanced Race Guide/Races/Dwarves/New Racial Rules/Dwarven Equipment/Waraxe/Dwarven Double", 
    "price": "60 gp", 
    "misc": {
        "Weapon": {
            "Weapon Class": "One-Handed Melee Weapons", 
            "Special": "see text", 
            "Dmg (S)": "1d8", 
            "Proficiency": "Exotic Weapons", 
            "Critical": "&times;3", 
            "Dmg (M)": "1d10", 
            "Dmg (L)": "2d8", 
            "Type": "S", 
            "Dmg (T)": "1d6"
        }
    }, 
    "source": "Advanced Race Guide", 
    "type": "item"
}