{
    "name": "Mounted Combat", 
    "url": "pfsrd://Core Rulebook/Feats/Mounted Combat", 
    "sections": [
        {
            "source": "Core Rulebook", 
            "type": "section", 
            "name": "Prerequisites", 
            "description": " Ride 1 rank."
        }, 
        {
            "body": "<p class=\"stat-block-1\"> Once per round when your mount is hit in combat, you may attempt a Ride check (as an immediate action) to negate the hit. The hit is negated if your Ride check result is greater than the opponent's attack roll.</p>", 
            "source": "Core Rulebook", 
            "type": "section", 
            "name": "Benefits"
        }
    ], 
    "source": "Core Rulebook", 
    "feat_types": {
        "feat_type": "Combat"
    }, 
    "type": "feat", 
    "description": "You are adept at guiding your mount through combat."
}