{
    "body": "<p id=\"14th-level-ki-powers\"></p><p>blood crow strike (2<i> ki </i>points)</p><p>Cloud Step (3<i> ki </i>points)</p><p>cold ice strike (3<i> ki </i>points)</p><p>diamond soul (monk ability)</p><p>Disarming Strike (2<i> ki </i>points)</p><p>Improved &lt;i&gt;Ki&lt;/i&gt; Throw (2<i> ki </i>points)</p><p>ki shout (3<i> ki </i>points)</p><p>sonic thrust (2<i> ki </i>points)</p>", 
    "url": "pfsrd://Ultimate Magic/Rules/Spellcasting Class Options/Monk/Monk Archetypes/Qinggong Monk/Ki Powers/14th-Level Ki Powers", 
    "type": "section", 
    "name": "14th-Level Ki Powers", 
    "source": "Ultimate Magic"
}