{
    "body": "<p id=\"wild-shape\">A mountain druid gains this ability at 6th level, except that her effective druid level for the ability is equal to her druid level &ndash; 2. A mountain druid cannot use wild shape to adopt a plant form. However, at 12th level she can assume the form of a Large giant as if using <i>giant form I</i>. At 16th level, she may assume the form of a Huge giant as if using <i>giant form II</i>.</p>", 
    "name": "Wild Shape", 
    "url": "pfsrd://Advanced Players Guide/Rules/Core Classes/Druid/Druid Archetypes/Mountain Druid/Wild Shape", 
    "ability_types": {
        "ability_type": "Supernatural"
    }, 
    "source": "Advanced Player's Guide", 
    "type": "ability"
}