{
    "dexterity": "17", 
    "ac": "29, touch 9, flat-footed 26 (+3 Dex, +20 natural, \u20134 size)", 
    "special_attacks": "absorb dying creature, energy drain (1 level, DC 26), trample (2d6+18, DC 31)", 
    "intelligence": "9", 
    "melee": "4 slams +21 (2d6+12 plus energy drain)", 
    "cr": "16", 
    "xp": "76,800", 
    "speed": "40 ft.", 
    "alignment": "NE", 
    "size": "Gargantuan", 
    "languages": "Common (can't speak)", 
    "strength": "34", 
    "constitution": "-", 
    "space": "20 ft.", 
    "treasure": "double standard (nonmagical armor and weapons)", 
    "init": "+3", 
    "environment": "any", 
    "source": "Bestiary 4", 
    "charisma": "25", 
    "immune": "undead traits", 
    "fortitude": "+13", 
    "spells": [
        {
            "spell-like abilities": "(CL 18th; concentration +25)<p class=\"stat-block-2\">3/day-extended <i>animate objects</i> (7 Medium weapons only), <i>telekinesis</i> (violent thrust, heavy armor only)</p>"
        }
    ], 
    "type": "creature", 
    "feats": "Awesome Blow, Blind-Fight, Greater Overrun, Improved Bull Rush, Improved Overrun, Lightning Reflexes, Power Attack, Step Up, Strike Back", 
    "senses": "darkvision 60 ft.; Perception +27", 
    "description": "An enormous, animate mass of armed and armored corpses undulates forth, like a siege tower of steel-girded flesh.", 
    "sections": [
        {
            "name": "Special Abilities", 
            "source": "Bestiary 4", 
            "url": "pfsrd://Bestiary 4/Monsters/Warsworn/Special Abilities", 
            "type": "section", 
            "subtype": "special_abilities", 
            "sections": [
                {
                    "body": "A warsworn can consume any dying creature by moving into the same space. This immediately kills the creature, absorbs the corpse into the warsworn, and heals the warsworn by an amount equal to the creature's Constitution score. Absorbed corpses can't be resurrected by any effect short of a miracle or wish until the warsworn that consumed them is destroyed.", 
                    "name": "Absorb Dying Creature", 
                    "url": "pfsrd://Bestiary 4/Monsters/Warsworn/Special Abilities/Absorb Dying Creature", 
                    "ability_types": {
                        "ability_type": "Supernatural"
                    }, 
                    "source": "Bestiary 4", 
                    "type": "ability"
                }, 
                {
                    "body": "Protection from evil blocks attacks from a warsworn's spell-like abilities. Weapons animated by the warsworn are damaged by channeled energy as if undead.", 
                    "name": "Profane Magic", 
                    "url": "pfsrd://Bestiary 4/Monsters/Warsworn/Special Abilities/Profane Magic", 
                    "ability_types": {
                        "ability_type": "Supernatural"
                    }, 
                    "source": "Bestiary 4", 
                    "type": "ability"
                }, 
                {
                    "body": "The warsworn can throw a mass of broken weapons and armor. This deals an amount of damage equal to 2d6 + the warsworn's Strength modifier, and has a range increment of 20 feet.", 
                    "name": "Scrap Ball", 
                    "url": "pfsrd://Bestiary 4/Monsters/Warsworn/Special Abilities/Scrap Ball", 
                    "ability_types": {
                        "ability_type": "Extraordinary"
                    }, 
                    "source": "Bestiary 4", 
                    "type": "ability"
                }
            ]
        }, 
        {
            "body": "<p>Warsworns are massive undead amalgams, their ever-shifting, chaotic bodies composed of countless slain soldiers and their armor and weapons. The shambling, serpentine form of a warsworn creates a grotesque, metallic cacophony as the weapons and armor of countless souls clash as though still in the throes of a never-ending battle.</p>", 
            "source": "Bestiary 4", 
            "type": "section"
        }, 
        {
            "body": "<p>A warsworn forms by the will of a god or goddess of undeath or war, or spontaneously from the bloodlust and wrath of a battlefield of dead soldiers. Once created, a warsworn exists to spread the rage of war, ravage the land, and spread the carnage of battle.</p>", 
            "source": "Bestiary 4", 
            "type": "section"
        }, 
        {
            "body": "<p>A typical warsworn weighs several tons and can reach a height of up to 25 feet. A newly formed one is much smaller, but quickly consumes nearby corpses from a battlefield or mass grave and swells to its full size. It is always hungry for more dying bodies. It prefers to absorb warriors and soldiers, but willingly consumes any suitable humanoid. Its constant grinding motion breaks its component parts, giving it plenty of scrap to hurl at distant foes.</p>", 
            "source": "Bestiary 4", 
            "type": "section"
        }
    ], 
    "hp": "207 (18d8+126)", 
    "reach": "5 ft.", 
    "wisdom": "22", 
    "defensive_abilities": "channel resistance +4", 
    "creature_type": "Undead", 
    "special_qualities": "profane magic", 
    "dr": "10/bludgeoning and magic", 
    "ranged": "1 scrap ball +12 (2d6+12)", 
    "name": "Warsworn", 
    "base_attack": "+13", 
    "skills": "Climb +33, Perception +27, Swim +30", 
    "reflex": "+9", 
    "cmd": "42 (can't be tripped)", 
    "cmb": "+29", 
    "will": "+17", 
    "url": "pfsrd://Bestiary 4/Monsters/Warsworn", 
    "aura": "frightful presence (60 ft., DC 26)", 
    "organization": "solitary"
}