{
    "body": "<table id=\"table-sphere-of-influence-modifiers\"><caption>Sphere of Influence Modifiers</caption><thead><tr><th>Action</th><th>Check Modifier</th></tr></thead><tr class=\"odd\"><td>Allies or minions spread tales of your deeds before you arrive</td><td>+5</td></tr><tr class=\"even\"><td>A bard spreads tales or songs of your deeds before you arrive</td><td>+ 1/2 bard level</td></tr><tr class=\"odd\"><td>You have NPC contacts in the settlement</td><td>+1</td></tr><tr class=\"even\"><td>You have enemies in the settlement</td><td>+1</td></tr><tr class=\"odd\"><td>Distance from your Sphere of Influence</td><td>&mdash;1 per 10 miles</td></tr><tr class=\"even\"><td>Settlement's primary language is different from yours</td><td>&mdash;5</td></tr></table>", 
    "url": "pfsrd://Ultimate Campaign/Rules/Campaign Systems/Reputation And Fame/Reputation and Fame/Sphere of Influence/Sphere of Influence Modifiers", 
    "type": "table", 
    "name": "Sphere of Influence Modifiers", 
    "source": "Ultimate Campaign"
}