{
    "name": "Blue or bronze dragon", 
    "url": "pfsrd://Ultimate Equipment/Rules/Wondrous Items/Slotless/Slotless Wondrous Items/Elixir of Dragon Breath/Blue or bronze dragon", 
    "sections": [
        {
            "body": "<p class=\"stat-block\">30-foot line of electricity.</p>", 
            "source": "Ultimate Equipment", 
            "type": "section", 
            "section_id": 2402
        }
    ], 
    "section_id": 2401, 
    "source": "Ultimate Equipment", 
    "type": "section"
}